MANIFEST.in
README.md
requirements.txt
requirements_api.txt
setup.py
shoot_ChatGPT.egg-info/PKG-INFO
shoot_ChatGPT.egg-info/SOURCES.txt
shoot_ChatGPT.egg-info/dependency_links.txt
shoot_ChatGPT.egg-info/entry_points.txt
shoot_ChatGPT.egg-info/requires.txt
shoot_ChatGPT.egg-info/top_level.txt
src/shoot_chatgpt/__init__.py
src/shoot_chatgpt/__main__.py
src/shoot_chatgpt/cloud_launcher.py
src/shoot_chatgpt/launcher.py
src/shoot_chatgpt/bots/__init__.py
src/shoot_chatgpt/bots/legacy.py
src/shoot_chatgpt/bots/server.py
src/shoot_chatgpt/exts/__init__.py
src/shoot_chatgpt/exts/config.py
src/shoot_chatgpt/exts/hooks.py
src/shoot_chatgpt/exts/sentry.py
src/shoot_chatgpt/exts/token.py
src/shoot_chatgpt/migrations/__init__.py
src/shoot_chatgpt/migrations/database.py
src/shoot_chatgpt/migrations/migrate.py
src/shoot_chatgpt/migrations/models.py
src/shoot_chatgpt/openai/__init__.py
src/shoot_chatgpt/openai/api.py
src/shoot_chatgpt/openai/auth.py
src/shoot_chatgpt/openai/token.py
src/shoot_chatgpt/openai/utils.py
src/shoot_chatgpt/turbo/__init__.py
src/shoot_chatgpt/turbo/base.py
src/shoot_chatgpt/turbo/chat.py