Metadata-Version: 2.1
Name: shoot-ChatGPT
Version: 1.2.7
Summary: A command-line interface to ChatGPT
Home-page: https://github.com/shoot82003/shoot_chatgpt
Author: shoot82003
Author-email: shoot82003@qq.com
Project-URL: Source, https://github.com/shoot82003/shoot_chatgpt
Project-URL: Tracker, https://github.com/shoot82003/shoot_chatgpt/issues
Keywords: OpenAI ChatGPT ChatGPT-Plus gpt-3.5-turbo gpt-3.5-turbo-0301
Classifier: Development Status :: 5 - Production/Stable
Classifier: Environment :: Console
Classifier: Environment :: Web Environment
Classifier: Framework :: Flask
Classifier: Intended Audience :: Developers
Classifier: Intended Audience :: End Users/Desktop
Classifier: License :: OSI Approved :: GNU General Public License v2 (GPLv2)
Classifier: Natural Language :: English
Classifier: Natural Language :: Chinese (Simplified)
Classifier: Operating System :: MacOS
Classifier: Operating System :: Microsoft :: Windows
Classifier: Operating System :: POSIX :: Linux
Classifier: Programming Language :: SQL
Classifier: Programming Language :: JavaScript
Classifier: Programming Language :: Python :: 3.7
Classifier: Programming Language :: Python :: 3.8
Classifier: Programming Language :: Python :: 3.9
Classifier: Programming Language :: Python :: 3.10
Classifier: Programming Language :: Python :: 3.11
Classifier: Topic :: Communications :: Chat
Classifier: Topic :: Internet :: WWW/HTTP
Requires-Python: >=3.7
Provides-Extra: api
Provides-Extra: cloud
